dragonfly_designbuilder/__init__.py
dragonfly_designbuilder/__main__.py
dragonfly_designbuilder/_extend_dragonfly.py
dragonfly_designbuilder/writer.py
dragonfly_designbuilder/cli/__init__.py
dragonfly_designbuilder/cli/translate.py
dragonfly_designbuilder-0.1.5.dist-info/licenses/LICENSE
dragonfly_designbuilder-0.1.5.dist-info/METADATA
dragonfly_designbuilder-0.1.5.dist-info/WHEEL
dragonfly_designbuilder-0.1.5.dist-info/entry_points.txt
dragonfly_designbuilder-0.1.5.dist-info/top_level.txt
dragonfly_designbuilder-0.1.5.dist-info/RECORD
