Metadata-Version: 2.4
Name: dragonfly-designbuilder
Version: 0.1.5
Summary: Dragonfly extension for the DOE-2 energy simulation engine.
Home-page: https://github.com/ladybug-tools/dragonfly-designbuilder
Author: Ladybug Tools
Author-email: info@ladybug.tools
License: AGPL-3.0
Classifier: Programming Language :: Python :: 3.9
Classifier: Programming Language :: Python :: 3.10
Classifier: Programming Language :: Python :: 3.11
Classifier: Programming Language :: Python :: 3.12
Classifier: Programming Language :: Python :: Implementation :: CPython
Classifier: Operating System :: OS Independent
License-File: LICENSE
Requires-Dist: honeybee-designbuilder==0.4.0
Requires-Dist: dragonfly-energy>=1.35.67
Dynamic: author
Dynamic: author-email
Dynamic: classifier
Dynamic: description
Dynamic: description-content-type
Dynamic: home-page
Dynamic: license
Dynamic: license-file
Dynamic: requires-dist
Dynamic: summary
